LICENSE
MANIFEST.in
README.rst
pytest_ansible_playbook.py
setup.py
pytest_ansible_playbook.egg-info/PKG-INFO
pytest_ansible_playbook.egg-info/SOURCES.txt
pytest_ansible_playbook.egg-info/dependency_links.txt
pytest_ansible_playbook.egg-info/entry_points.txt
pytest_ansible_playbook.egg-info/requires.txt
pytest_ansible_playbook.egg-info/top_level.txt