Metadata-Version: 1.1
Name: pytest-ansible-playbook
Version: 0.3.0
Summary: Pytest fixture which runs given ansible playbook file.
Home-page: https://gitlab.com/mbukatov/pytest-ansible-playbook
Author: Martin Bukatovič
Author-email: mbukatov@redhat.com
License: Apache 2.0
Platform: UNKNOWN
Classifier: Development Status :: 4 - Beta
Classifier: Framework :: Pytest
Classifier: Intended Audience :: Developers
Classifier: Topic :: Software Development :: Testing
Classifier: Programming Language :: Python
Classifier: Programming Language :: Python :: 2
Classifier: Programming Language :: Python :: 2.7
Classifier: Programming Language :: Python :: 3
Classifier: Programming Language :: Python :: 3.5
Classifier: Programming Language :: Python :: Implementation :: CPython
Classifier: Programming Language :: Python :: Implementation :: PyPy
Classifier: Operating System :: POSIX
